mpl_bsic/__init__.py
mpl_bsic/apply_bsic_logo.py
mpl_bsic/apply_bsic_style.py
mpl_bsic/check_figsize.py
mpl_bsic/export_figure.py
mpl_bsic/fonts/garamond/Garamond.TTF
mpl_bsic/fonts/garamond/Garamond_Bold.TTF
mpl_bsic/fonts/garamond/Garamond_Italic.TTF
mpl_bsic/fonts/gill_sans_mt/GillSansMT_Base.ttf
mpl_bsic/fonts/gill_sans_mt/GillSansMT_Bold.TTF
mpl_bsic/fonts/gill_sans_mt/GillSansMT_BoldItalic.TTF
mpl_bsic/fonts/gill_sans_mt/GillSansMT_Italic.TTF
mpl_bsic/format_timeseries_axis.py
mpl_bsic/plot_trade.py
mpl_bsic/preprocess_dataframe.py
mpl_bsic/static/bsic_logo_formal_1x.png
mpl_bsic/static/bsic_logo_formal_2x.png
mpl_bsic/static/bsic_logo_formal_3x.png
mpl_bsic/static/bsic_logo_square_1x.png
mpl_bsic/static/bsic_logo_square_2x.png
mpl_bsic/static/bsic_logo_square_3x.png
mpl_bsic/style_excel.py
utils/__init__.py
utils/add_fonts.py
utils/run_animations.py
utils/set_animations.py
mpl_bsic-1.3.1.dist-info/LICENSE.md
mpl_bsic-1.3.1.dist-info/METADATA
mpl_bsic-1.3.1.dist-info/WHEEL
mpl_bsic-1.3.1.dist-info/RECORD
