Metadata-Version: 2.1
Name: mpl_bsic
Version: 1.3.1
Summary: BSIC Plotting Library
Author: Andrea Franceschini
Author-email: andrea.franceschini2@studbocconi.it
Requires-Python: >=3.9
Classifier: Programming Language :: Python :: 3
Classifier: Programming Language :: Python :: 3.9
Classifier: Programming Language :: Python :: 3.10
Classifier: Programming Language :: Python :: 3.11
Classifier: Programming Language :: Python :: 3.12
Requires-Dist: matplotlib (>=3.7,<4.0)
Requires-Dist: numpy (>=1.25,<2.0)
Requires-Dist: pandas (>=2,<3)
Requires-Dist: xlsxwriter (>=3.2.0,<4.0.0)
